gtaccelerate/__init__.py
gtaccelerate/loops/__init__.py
gtaccelerate/loops/evaluation/__init__.py
gtaccelerate/loops/evaluation/accelerate.py
gtaccelerate/loops/training/__init__.py
gtaccelerate/loops/training/accelerate.py
gtaccelerate-0.0.1a6.dist-info/LICENSE
gtaccelerate-0.0.1a6.dist-info/METADATA
gtaccelerate-0.0.1a6.dist-info/WHEEL
gtaccelerate-0.0.1a6.dist-info/RECORD
